{"001":{"r":"N554TS","t":"C560"},"00A":{"r":"N554UA","t":"B752"},"01A":{"r":"N554US","t":"BE55"},"01E":{"r":"N554UW","t":"A321"},"030":{"r":"N554VP","t":"C560"},"032":{"r":"N554VR","t":"PC12"},"047":{"r":"N554WM","t":"C182"},"048":{"r":"N554WN","t":"B737"},"0ED":{"r":"N5542H","t":"C152"},"0F2":{"r":"N5542N","t":"C182"},"101":{"r":"N55423","t":"P28R"},"102":{"r":"N55424","t":"TOBA"},"163":{"r":"N619NK","t":"A320"},"17A":{"r":"N5546J","t":"C172"},"1BF":{"r":"N5548H","t":"TOBA"},"1DB":{"r":"N5549A","t":"C210"},"1E7":{"r":"N5549N","t":"C182"},"1E9":{"r":"N5549Q","t":"M20P"},"1FD":{"r":"N555","t":"ST75"},"201":{"r":"N555AC","t":"BL8"},"209":{"r":"N555AL","t":"B350"},"20B":{"r":"N555AN","t":"MD82"},"20C":{"r":"N555AP","t":"TS1J"},"210":{"r":"N555AT","t":"PAY1"},"211":{"r":"N555AU","t":"P46T"},"215":{"r":"N555AY","t":"A321"},"21E":{"r":"N555BG","t":"C525"},"221":{"r":"N555BK","t":"C550"},"224":{"r":"N555BN","t":"R44"},"225":{"r":"N555BP","t":"P32R"},"229":{"r":"N555BT","t":"PA34"},"22B":{"r":"N555BV","t":"LNC4"},"232":{"r":"N555CB","t":"SR22"},"23A":{"r":"N555CK","t":"LJ45"},"23E":{"r":"N555CP","t":"C340"},"242":{"r":"N555CT","t":"P32R"},"248":{"r":"N555CZ","t":"C182"},"258":{"r":"N555DQ","t":"TBM8"},"25E":{"r":"N555DW","t":"GLF3"},"262":{"r":"N555E","t":"BE35"},"266":{"r":"N555ED","t":"M20P"},"26A":{"r":"N555EH","t":"LJ60"},"26D":{"r":"N555EL","t":"R44"},"272":{"r":"N555ER","t":"C182"},"277":{"r":"N555EW","t":"PC12"},"27F":{"r":"N555FD","t":"C560"},"283":{"r":"N555FH","t":"BE30"},"288":{"r":"N555FN","t":"C172"},"28B":{"r":"N555FR","t":"PAY1"},"28F":{"r":"N555FV","t":"BE9L"},"290":{"r":"N555FW","t":"BE20"},"297":{"r":"N555GC","t":"M20P"},"29B":{"r":"N555GG","t":"BE35"},"29C":{"r":"N555GH","t":"C182"},"29D":{"r":"N555GJ","t":"EC20"},"29F":{"r":"N555GL","t":"GLF3"},"2A5":{"r":"N555GS","t":"F2TH"},"2A6":{"r":"N555GT","t":"PA31"},"2A8":{"r":"N555GV","t":"GLF5"},"2B1":{"r":"N555HD","t":"GL5T"},"2B4":{"r":"N555HG","t":"C208"},"2B6":{"r":"N555HJ","t":"BE9L"},"2B9":{"r":"N555HM","t":"C550"},"2BB":{"r":"N555HP","t":"TBM8"},"2BD":{"r":"N555HR","t":"M20T"},"2C7":{"r":"N555JA","t":"C560"},"2CA":{"r":"N555JD","t":"C310"},"2D0":{"r":"N555JK","t":"CH7A"},"2E4":{"r":"N555KE","t":"ASTR"},"2E6":{"r":"N555KG","t":"RV8"},"2EA":{"r":"N555KL","t":"P28R"},"2F1":{"r":"N555KT","t":"C560"},"2F8":{"r":"N555L","t":"PA34"},"2FC":{"r":"N555LD","t":"RV7"},"2FE":{"r":"N555LF","t":"BE35"},"2FF":{"r":"N555LG","t":"C560"},"302":{"r":"N555LK","t":"GLF4"},"308":{"r":"N555LR","t":"GLF4"},"30C":{"r":"N555LV","t":"B737"},"312":{"r":"N555MA","t":"GLAS"},"313":{"r":"N555MB","t":"C680"},"314":{"r":"N555MC","t":"BE20"},"323":{"r":"N555MT","t":"AC90"},"325":{"r":"N555MV","t":"C310"},"337":{"r":"N555NN","t":"CRJ9"},"33E":{"r":"N555NV","t":"C182"},"33F":{"r":"N555NW","t":"B752"},"343":{"r":"N555P","t":"BE55"},"34F":{"r":"N555PM","t":"PAY1"},"35E":{"r":"N555QB","t":"C750"},"36D":{"r":"N555QS","t":"C56X"},"37A":{"r":"N555RE","t":"GLF3"},"37B":{"r":"N555RF","t":"C421"},"387":{"r":"N555RT","t":"C551"},"394":{"r":"N555SF","t":"BE35"},"397":{"r":"N555SJ","t":"B06"},"398":{"r":"N555SK","t":"C210"},"399":{"r":"N555SL","t":"C172"},"39B":{"r":"N555SN","t":"BE35"},"3AD":{"r":"N555TF","t":"GLF4"},"3B0":{"r":"N555TJ","t":"M20P"},"3B1":{"r":"N555TK","t":"BE55"},"3B5":{"r":"N555TP","t":"P32R"},"3B6":{"r":"N555TQ","t":"TBM8"},"3B9":{"r":"N555TT","t":"SR22"},"3C1":{"r":"N555UA","t":"B752"},"3C9":{"r":"N555UJ","t":"PA34"},"3DA":{"r":"N555VA","t":"COL4"},"3E9":{"r":"N555VR","t":"LJ45"},"3EE":{"r":"N555VW","t":"BE9L"},"3F3":{"r":"N555WA","t":"EXPL"},"3F4":{"r":"N555WB","t":"C172"},"3F6":{"r":"N555WD","t":"CL60"},"3F7":{"r":"N555WE","t":"BE20"},"3FD":{"r":"N555WL","t":"C560"},"400":{"r":"N555WP","t":"C414"},"401":{"r":"N555WQ","t":"B350"},"404":{"r":"N555WT","t":"BE33"},"40A":{"r":"N555WZ","t":"C56X"},"41C":{"r":"N555XS","t":"GLF3"},"41D":{"r":"N555XT","t":"LNP4"},"422":{"r":"N555XY","t":"BE9L"},"435":{"r":"N555YS","t":"C172"},"43A":{"r":"N555YX","t":"WAIX"},"43E":{"r":"N555ZA","t":"B350"},"484":{"r":"N5551L","t":"C152"},"488":{"r":"N5551Q","t":"TB20"},"48C":{"r":"N5551U","t":"TB20"},"48D":{"r":"N5551V","t":"BE36"},"49C":{"r":"N5552","t":"BE33"},"4A3":{"r":"N5552G","t":"TB20"},"4AB":{"r":"N5552Q","t":"M20P"},"4BF":{"r":"N5553","t":"WACF"},"4C0":{"r":"N5553A","t":"C206"},"4C4":{"r":"N5553E","t":"C182"},"4E9":{"r":"N5554G","t":"C421"},"509":{"r":"N5555D","t":"C182"},"516":{"r":"N5555S","t":"P210"},"51E":{"r":"N55550","t":"BE36"},"523":{"r":"N55555","t":"NORS"},"53D":{"r":"N5556W","t":"RV7"},"546":{"r":"N55565","t":"P28A"},"5B6":{"r":"N556AA","t":"MD82"},"5B8":{"r":"N556AC","t":"H500"},"5BA":{"r":"N556AE","t":"AS50"},"5BB":{"r":"N556AF","t":"GLF3"},"5C0":{"r":"N556AL","t":"BE20"},"5C1":{"r":"N556AM","t":"AS50"},"5C6":{"r":"N556AS","t":"B738"},"5CF":{"r":"N556BA","t":"BE20"},"5D5":{"r":"N556BG","t":"C560"},"5E8":{"r":"N556CA","t":"P46T"},"5E9":{"r":"N556CB","t":"SR22"},"5EE":{"r":"N556CG","t":"LJ45"},"5F5":{"r":"N556CP","t":"H500"},"629":{"r":"N556ER","t":"C172"},"637":{"r":"N556FE","t":"DC10"},"64B":{"r":"N556G","t":"RV10"},"64C":{"r":"N556GA","t":"CRUZ"},"668":{"r":"N556HD","t":"FA50"},"66F":{"r":"05-0556","t":"PC12"},"67F":{"r":"N556JB","t":"A320"},"689":{"r":"N556JM","t":"DA40"},"6B5":{"r":"N556LF","t":"A119"},"6BB":{"r":"N556LM","t":"AVID"},"6C0":{"r":"N556LS","t":"C56X"},"6CA":{"r":"N556MB","t":"C421"},"6CE":{"r":"N556MF","t":"B06"},"6EE":{"r":"N556NN","t":"CRJ9"},"6F6":{"r":"N556NW","t":"B752"},"706":{"r":"N556PM","t":"DH8B"},"724":{"r":"N556QS","t":"C56X"},"72D":{"r":"N556RA","t":"C650"},"755":{"r":"N556SR","t":"SR22"},"770":{"r":"N556TT","t":"GLF5"},"778":{"r":"N556UA","t":"B752"},"78C":{"r":"N556UW","t":"A321"},"7B6":{"r":"N556WN","t":"B737"},"814":{"r":"N5560G","t":"C421"},"815":{"r":"N5660H","t":"PA11"},"888":{"r":"N5563T","t":"C172"},"8C0":{"r":"N5565D","t":"BE58"},"922":{"r":"N55677","t":"P28R"},"948":{"r":"N5569","t":"GLF5"},"955":{"r":"N5569N","t":"BE36"},"956":{"r":"N5569P","t":"PA24"},"971":{"r":"N557AE","t":"AS50"},"972":{"r":"N557AF","t":"DA40"},"978":{"r":"N557AM","t":"AS50"},"979":{"r":"N557AN","t":"MD82"},"97D":{"r":"N557AS","t":"B738"},"980":{"r":"N557AV","t":"A319"},"98F":{"r":"N557BK","t":"LJ31"},"9A3":{"r":"N557CE","t":"BE58"},"9A5":{"r":"N557CG","t":"PA12"},"9AA":{"r":"N557CM","t":"B752"},"9AC":{"r":"N557CP","t":"H500"},"9AF":{"r":"N557CS","t":"C550"},"9E0":{"r":"N557ER","t":"C172"},"9FE":{"r":"N557FW","t":"B407"},"A03":{"r":"N557GA","t":"G150"},"A1B":{"r":"N557H","t":"GLF5"},"A1F":{"r":"N557HD","t":"KODI"},"A29":{"r":"N557HP","t":"C525"},"A3E":{"r":"N557JK","t":"GLF3"},"A8A":{"r":"N557ML","t":"PA46"},"AA5":{"r":"N557NN","t":"CRJ9"},"AAD":{"r":"N557NW","t":"B752"},"AB1":{"r":"N557P","t":"BE9L"},"AB8":{"r":"N557PG","t":"C560"},"ABB":{"r":"N557PK","t":"LJ31"},"AC2":{"r":"N557PS","t":"DA40"},"ADB":{"r":"N557QS","t":"C56X"},"AE4":{"r":"N557RA","t":"RV7"},"AFF":{"r":"N557SC","t":"BE30"},"B0E":{"r":"N557ST","t":"B430"},"B17":{"r":"N557TB","t":"TB20"},"B18":{"r":"N557TC","t":"E50P"},"B2F":{"r":"N557UA","t":"B752"},"B36":{"r":"N557UH","t":"B430"},"B3F":{"r":"N557US","t":"M20T"},"B43":{"r":"N557UW","t":"A321"},"B59":{"r":"N557VT","t":"BE36"},"B6D":{"r":"N557WN","t":"B737"},"B77":{"r":"N557WY","t":"GLF4"},"B79":{"r":"N557X","t":"RV6"},"B82":{"r":"N557XJ","t":"CL30"},"B87":{"r":"YV457T","t":"BE40"},"BEB":{"r":"N5571D","t":"BE33"},"BF5":{"r":"N5571P","t":"PA24"},"C1D":{"r":"N5572U","t":"P28A"},"C29":{"r":"N55726","t":"P28R"},"C3E":{"r":"N5573S"},"CB2":{"r":"N55763","t":"P28R"},"CD3":{"r":"N55771","t":"P28A"},"CFA":{"r":"N55785","t":"P28A"},"D06":{"r":"N5579G","t":"C150"},"D0B":{"r":"N5579M","t":"BE33"},"D24":{"r":"N558AA","t":"MD82"},"D25":{"r":"N558AB","t":"BE58"},"D2F":{"r":"N558AM"},"D34":{"r":"N558AS","t":"B738"},"D39":{"r":"N558AX","t":"B752"},"D3F":{"r":"N558BC","t":"B350"},"D55":{"r":"N558C","t":"S108"},"D57":{"r":"N558CB","t":"BE55"},"D59":{"r":"N558CD","t":"SR22"},"D60":{"r":"N558CL","t":"B744"},"D75":{"r":"N558DG","t":"R44"},"D97":{"r":"N558ER","t":"C172"},"DBA":{"r":"N558GA","t":"GLF5"},"DD4":{"r":"N558HB","t":"BE58"},"DED":{"r":"N558JB","t":"A320"},"DFD":{"r":"N558JT","t":"PA46"},"E36":{"r":"N558M","t":"M20P"},"E39":{"r":"N558MC","t":"A500"},"E48":{"r":"N558MT","t":"EC35"},"E5C":{"r":"N558NN","t":"CRJ9"},"E68":{"r":"N558P","t":"BE58"},"E6F":{"r":"N558PG","t":"SR22"},"E92":{"r":"N558QS","t":"C56X"},"E9A":{"r":"N558R","t":"C56X"},"EA6":{"r":"N558RM","t":"M20P"},"EC1":{"r":"N558SP","t":"B06"},"EC5":{"r":"N558ST","t":"PA46"},"ECD":{"r":"N558TA","t":"C206"},"EE6":{"r":"N558UA","t":"B752"},"EFA":{"r":"N558UW","t":"A321"},"F19":{"r":"N558WB","t":"C550"},"F1F":{"r":"N558WH","t":"BE58"},"F24":{"r":"N558WN","t":"B737"},"F2C":{"r":"N558WW","t":"C560"},"F3E":{"r":"N558XP","t":"BE40"},"FF4":{"r":"N5583R","t":"CH70"}}