{"005":{"r":"N9770G","t":"C182"},"009":{"r":"N9770L","t":"BE23"},"024":{"r":"N9771C","t":"CL60"},"0A2":{"r":"N9774Z","t":"C206"},"0BF":{"r":"N9775T","t":"PA38"},"0E7":{"r":"N9776Y","t":"C210"},"0F7":{"r":"N9777D","t":"PA18"},"146":{"r":"N9779N","t":"ALIG"},"15C":{"r":"N978","t":"C310"},"163":{"r":"N978AF","t":"PC12"},"16A":{"r":"N978AN","t":"B738"},"16B":{"r":"N978AP","t":"C172"},"16F":{"r":"N978AT","t":"B712"},"173":{"r":"N978AX","t":"DC94"},"176":{"r":"N978B","t":"BE50"},"17B":{"r":"N978BE","t":"C680"},"192":{"r":"N978CC","t":"GLF4"},"19B":{"r":"N978CM","t":"RV7"},"1AA":{"r":"N978DB","t":"C750"},"1B3":{"r":"N978DL","t":"MD88"},"1D5":{"r":"N978EV","t":"CRJ2"},"1DE":{"r":"N978FD","t":"B752"},"1FD":{"r":"N978GK","t":"BE36"},"253":{"r":"N978KW","t":"C182"},"296":{"r":"N978NN","t":"B738"},"2A2":{"r":"N978P","t":"PA34"},"2A5":{"r":"N978PC","t":"C510"},"2B7":{"r":"N978PW","t":"F900"},"2CC":{"r":"N978QS","t":"C750"},"2D5":{"r":"N978RA","t":"C182"},"2DC":{"r":"N978RH","t":"B06"},"2EF":{"r":"N978SB","t":"PC12"},"2FD":{"r":"N978SR","t":"SR22"},"302":{"r":"N978SW","t":"CRJ2"},"310":{"r":"N978TK","t":"B739"},"317":{"r":"N978TS","t":"B350"},"31B":{"r":"N978TW","t":"MD83"},"336":{"r":"N978UY","t":"A321"},"338":{"r":"N978V","t":"A139"},"3C4":{"r":"N9780Q","t":"AEST"},"402":{"r":"N9782G","t":"C180"},"415":{"r":"N97821","t":"M20P"},"41A":{"r":"N97826","t":"C208"},"451":{"r":"N9784R","t":"BE35"},"474":{"r":"N9785R","t":"BE35"},"4AC":{"r":"N9787B","t":"C72R"},"4F7":{"r":"N9789G","t":"C180"},"510":{"r":"N97897","t":"C182"},"521":{"r":"N979AN","t":"B738"},"525":{"r":"N979AS","t":"ZZZZ"},"526":{"r":"N979AT","t":"B712"},"52A":{"r":"N979AX","t":"DC94"},"52E":{"r":"N979BA","t":"BE36"},"546":{"r":"N979C","t":"P28A"},"547":{"r":"N979CA","t":"C172"},"548":{"r":"N979CB","t":"GLEX"},"54C":{"r":"N979CF","t":"H25B"},"552":{"r":"N979CM","t":"BE40"},"56A":{"r":"N979DL","t":"MD88"},"56B":{"r":"N979DM","t":"BE55"},"56F":{"r":"N979DR","t":"LJ45"},"58C":{"r":"N979EV","t":"CRJ2"},"595":{"r":"N979FD","t":"B752"},"5C4":{"r":"N979HA","t":"DH8A"},"608":{"r":"N979KU","t":"B412"},"628":{"r":"N979MA","t":"BE36"},"629":{"r":"N979MB","t":"TBM7"},"641":{"r":"N979NA","t":"BE36"},"64D":{"r":"N979NN","t":"B738"},"651":{"r":"N979NS","t":"MD83"},"66A":{"r":"N979PS","t":"BE20"},"672":{"r":"N979Q","t":"BE33"},"683":{"r":"N979QS","t":"C750"},"68F":{"r":"N979RD","t":"LJ55"},"693":{"r":"N979RH","t":"B06"},"699":{"r":"N979RP","t":"E170"},"69F":{"r":"N979RV","t":"RV9"},"6AA":{"r":"N979SF","t":"C182"},"6B9":{"r":"N979SW","t":"CRJ2"},"6BF":{"r":"N979TB","t":"H25B"},"6C9":{"r":"N979TM","t":"HA4T"},"6D2":{"r":"N979TW","t":"MD83"},"6ED":{"r":"N979UY","t":"A321"},"70C":{"r":"N979WD","t":"C172"},"797":{"r":"N9791H","t":"C182"},"7A8":{"r":"N97910","t":"S108"},"7AA":{"r":"N97912","t":"C182"},"7DA":{"r":"N9793E","t":"BL17"},"7DD":{"r":"N9793H","t":"C182"},"841":{"r":"N9796C","t":"P32T"},"846":{"r":"N9796H","t":"C182"},"897":{"r":"N9798U","t":"AA5"},"8AF":{"r":"N9799H","t":"C182"},"8C3":{"r":"N97993","t":"C182"},"8CE":{"r":"N98AC","t":"FA50"},"8D2":{"r":"N98AG","t":"P68"},"8D4":{"r":"N98AJ","t":"AC90"},"8D6":{"r":"N98AL","t":"B06"},"8DB":{"r":"N98AR","t":"BE9L"},"8DC":{"r":"N98AS","t":"FA20"},"8E0":{"r":"N98AW","t":"SR22"},"8E3":{"r":"N98AZ","t":"B06"},"8F9":{"r":"N98BW","t":"C421"},"905":{"r":"N98CH","t":"C25C"},"908":{"r":"N98CL","t":"B06"},"916":{"r":"N98D","t":"RV8"},"917":{"r":"N98DA","t":"RV7"},"91E":{"r":"N98DH","t":"C25A"},"92F":{"r":"N98E","t":"C560"},"931":{"r":"N98EB","t":"SW3"},"94F":{"r":"N98FG","t":"C750"},"953":{"r":"N98FL","t":"M20T"},"95A":{"r":"N98FT","t":"H25B"},"962":{"r":"N98GA","t":"M20P"},"976":{"r":"N98GW","t":"BE60"},"97C":{"r":"N98HB","t":"BE9L"},"981":{"r":"N98HG","t":"WW24"},"9A5":{"r":"N98JT","t":"M20T"},"9A7":{"r":"N98JV","t":"LJ60"},"9BB":{"r":"N98KQ","t":"KODI"},"9BD":{"r":"N98KS","t":"BE9L"},"9D0":{"r":"N98LL","t":"C340"},"9D5":{"r":"N98LR","t":"BE36"},"9D7":{"r":"N98LT","t":"GLF4"},"9DA":{"r":"N98LW","t":"SR22"},"9F3":{"r":"N98MW","t":"BE33"},"9FD":{"r":"N98NF","t":"TBM7"},"9FE":{"r":"N98NG","t":"C206"},"A0D":{"r":"N98NX","t":"F900"},"A19":{"r":"N98PJ","t":"AC90"},"A29":{"r":"N98Q","t":"C500"},"A43":{"r":"N98RA","t":"BE20"},"A46":{"r":"N98RD","t":"AEST"},"A47":{"r":"N98RE","t":"BE58"},"A50":{"r":"N98RP","t":"F2TH"},"A5E":{"r":"N98SC","t":"BE50"},"A67":{"r":"N98SM","t":"B06"},"A6F":{"r":"N98SV","t":"C402"},"A71":{"r":"N98SX","t":"SONX"},"A78":{"r":"N98TD","t":"C182"},"A79":{"r":"N98TE","t":"AS50"},"A7B":{"r":"N98TG","t":"PAY1"},"A7C":{"r":"N98TH","t":"F2TH"},"A90":{"r":"N98UC","t":"SW3"},"A9F":{"r":"N98UT","t":"COL4"},"AA8":{"r":"N98VB","t":"C182"},"AB1":{"r":"N98VL","t":"R44"},"AB2":{"r":"N98VM","t":"M20P"},"AC7":{"r":"N98WH","t":"C182"},"AC8":{"r":"N98WJ","t":"GLF2"},"ACD":{"r":"N98WP","t":"BE9L"},"AD6":{"r":"N98WY","t":"C182"},"AD7":{"r":"N98WZ","t":"PA11"},"AE3":{"r":"N98XL","t":"C56X"},"AE9":{"r":"N98XS","t":"C650"},"B1C":{"r":"N98ZT","t":"C172"},"B29":{"r":"N980AE","t":"EC45"},"B2B":{"r":"N980AG","t":"C560"},"B30":{"r":"N980AM","t":"C340"},"B31":{"r":"N980AN","t":"B738"},"B34":{"r":"N980AR","t":"BE9T"},"B36":{"r":"N980AT","t":"B712"},"B38":{"r":"N980AV","t":"A320"},"B40":{"r":"N980BC","t":"B350"},"B45":{"r":"N980BH","t":"AC95"},"B52":{"r":"N980BW","t":"B733"},"B57":{"r":"N980CA","t":"PAY1"},"B71":{"r":"N980DB","t":"GLSP"},"B7A":{"r":"N980DL","t":"MD88"},"B80":{"r":"N980DS","t":"DA40"},"B9C":{"r":"N980EV","t":"CRJ2"},"BA6":{"r":"N980FE","t":"C208"},"BBC":{"r":"N980GB","t":"BE20"},"BC1":{"r":"N980GG","t":"GLEX"},"BCA":{"r":"N980GR","t":"AC95"},"BD5":{"r":"N980HB","t":"AC95"},"BEF":{"r":"N980JC","t":"CL30"},"C3C":{"r":"N980ME","t":"EC45"},"C5D":{"r":"N980NN","t":"B738"},"CB4":{"r":"N980S","t":"FA50"},"CB6":{"r":"N980SB","t":"DC94"},"CBA":{"r":"N980SF","t":"F900"},"CC6":{"r":"N980ST","t":"B734"},"CC9":{"r":"N980SW","t":"CRJ2"},"CE2":{"r":"N980TW","t":"MD83"},"CFD":{"r":"N980UY","t":"A321"},"D0D":{"r":"N980VP","t":"C525"},"DA2":{"r":"N9801C","t":"T6"},"DA5":{"r":"N9801F","t":"L5"},"DBD":{"r":"N98015","t":"P28A"},"DC3":{"r":"N9802A","t":"PA44"},"DDA":{"r":"N9802Z","t":"C206"},"E4F":{"r":"N9806A","t":"RV6"},"EC0":{"r":"N9809J","t":"C150"},"EE0":{"r":"N981AE","t":"EC45"},"EE2":{"r":"N981AG","t":"C560"},"EE8":{"r":"N981AN","t":"B738"},"EEB":{"r":"N981AR","t":"B350"},"EEC":{"r":"N981AS","t":"MD83"},"EED":{"r":"N981AT","t":"B712"},"EF1":{"r":"N981AX","t":"DC93"},"EF6":{"r":"N981BB","t":"BE20"},"F12":{"r":"N981CE","t":"H25B"},"F27":{"r":"N981DA","t":"SRAY"},"F31":{"r":"N981DL","t":"MD88"},"F32":{"r":"N981DM","t":"C340"},"F37":{"r":"N981DS","t":"SR22"},"F44":{"r":"N981EE","t":"E190"},"F53":{"r":"N981EV","t":"CRJ2"},"F5D":{"r":"N981FE","t":"C208"},"F83":{"r":"N981GT","t":"C206"},"FC8":{"r":"N981KM","t":"E300"},"FE0":{"r":"N981LL","t":"B350"},"FF1":{"r":"N981MC","t":"AEST"}}